sql_model_cleaner/__init__.py
sql_model_cleaner/main.py
cbcsqlcleaner-0.1.0.dist-info/METADATA
cbcsqlcleaner-0.1.0.dist-info/WHEEL
cbcsqlcleaner-0.1.0.dist-info/entry_points.txt
cbcsqlcleaner-0.1.0.dist-info/top_level.txt
cbcsqlcleaner-0.1.0.dist-info/RECORD
